setup.py
Spike_Count_Models.egg-info/PKG-INFO
Spike_Count_Models.egg-info/SOURCES.txt
Spike_Count_Models.egg-info/dependency_links.txt
Spike_Count_Models.egg-info/top_level.txt
spikecountmodels/__init__.py
spikecountmodels/chitest.py
spikecountmodels/comppoissmodel.py
spikecountmodels/config.py
spikecountmodels/copula.py
spikecountmodels/copulamodel.py
spikecountmodels/isingmodel.py
spikecountmodels/marginal.py
spikecountmodels/model.py