Metadata-Version: 1.0
Name: Spike-Count-Models
Version: 0.1
Summary: This package provides a multitude of statistical tests, copulas and marginal distribution with functions for fitting data, calculating likelihoods and generate samples... Its intended purpose was modeling spike counts, but it can be used for other tasks.
Home-page: UNKNOWN
Author: Arno Onken
Author-email: aonken@cs.tu-berlin.de
License: GNU
Keywords: copula distributions statistical modelling tests marginals maximum likelihood spike computational neuroscience
Platform: UNKNOWN
Classifier: Development Status :: 5 - Production/Stable 
Classifier: Environment :: Console
Classifier: Intended Audience :: Science/Research
Classifier: Topic :: Utilities
Classifier: License :: OSI Approved :: GNU General Public License (GPL)
Classifier: Programming Language :: Python :: 2.6
Classifier: Topic :: Scientific/Engineering
